{
	"info": {
		"_postman_id": "907e0b4d-1ae2-4769-84ea-7b66f8d7a6ec",
		"name": "Live_Agenda",
		"schema": "https://schema.getpostman.com/json/collection/v2.1.0/collection.json",
		"_exporter_id": "25584133"
	},
	"item": [
		{
			"name": "Tasks",
			"item": [
				{
					"name": "AddTask",
					"request": {
						"method": "POST",
						"header": [],
						"body": {
							"mode": "raw",
							"raw": "{\r\n    \"description\": \"1st task\"\r\n}",
							"options": {
								"raw": {
									"language": "json"
								}
							}
						},
						"url": {
							"raw": "http://localhost:5000/tasks",
							"protocol": "http",
							"host": [
								"localhost"
							],
							"port": "5000",
							"path": [
								"tasks"
							]
						}
					},
					"response": []
				},
				{
					"name": "GetTask",
					"request": {
						"method": "GET",
						"header": [],
						"url": {
							"raw": "http://localhost:5000/tasks",
							"protocol": "http",
							"host": [
								"localhost"
							],
							"port": "5000",
							"path": [
								"tasks"
							]
						}
					},
					"response": []
				},
				{
					"name": "DeleteTask",
					"request": {
						"method": "DELETE",
						"header": [],
						"url": {
							"raw": "http://localhost:5000/tasks/66a758388668d8d63c80f184",
							"protocol": "http",
							"host": [
								"localhost"
							],
							"port": "5000",
							"path": [
								"tasks",
								"66a758388668d8d63c80f184"
							]
						}
					},
					"response": []
				},
				{
					"name": "UpdateTask",
					"request": {
						"method": "PUT",
						"header": [],
						"body": {
							"mode": "raw",
							"raw": "{\r\n    \"description\": \"updated task\",\r\n    \"completed\": true\r\n}",
							"options": {
								"raw": {
									"language": "json"
								}
							}
						},
						"url": {
							"raw": "http://localhost:5000/tasks/66a75ba037833ee5d256cc66",
							"protocol": "http",
							"host": [
								"localhost"
							],
							"port": "5000",
							"path": [
								"tasks",
								"66a75ba037833ee5d256cc66"
							]
						}
					},
					"response": []
				}
			]
		},
		{
			"name": "Restaurants",
			"item": [
				{
					"name": "AddRestaurant",
					"request": {
						"method": "POST",
						"header": [],
						"body": {
							"mode": "raw",
							"raw": "{\r\n    \"name\": \"Daikiri\",\r\n    \"location\": \"Madalena\",\r\n    \"description\": \"Peixe Carne\"\r\n}",
							"options": {
								"raw": {
									"language": "json"
								}
							}
						},
						"url": {
							"raw": "http://localhost:5000/restaurants",
							"protocol": "http",
							"host": [
								"localhost"
							],
							"port": "5000",
							"path": [
								"restaurants"
							]
						}
					},
					"response": []
				},
				{
					"name": "GetRestaurants",
					"request": {
						"method": "GET",
						"header": [],
						"url": {
							"raw": "http://localhost:5000/restaurants",
							"protocol": "http",
							"host": [
								"localhost"
							],
							"port": "5000",
							"path": [
								"restaurants"
							]
						}
					},
					"response": []
				},
				{
					"name": "DeleteRestaurant",
					"request": {
						"method": "DELETE",
						"header": [],
						"url": {
							"raw": "http://localhost:5000/restaurants/66b0037447bbfebf82de29fe",
							"protocol": "http",
							"host": [
								"localhost"
							],
							"port": "5000",
							"path": [
								"restaurants",
								"66b0037447bbfebf82de29fe"
							]
						}
					},
					"response": []
				},
				{
					"name": "UpdateRestaurant",
					"request": {
						"method": "PUT",
						"header": [],
						"body": {
							"mode": "raw",
							"raw": "{\r\n    \"name\": \"Sabor a Mar\",\r\n    \"location\": \"Aguda\",\r\n    \"description\": \"Filetes de Pescada\"\r\n}",
							"options": {
								"raw": {
									"language": "json"
								}
							}
						},
						"url": {
							"raw": "http://localhost:5000/restaurants/66af7f40e70a3ed181fc70a1",
							"protocol": "http",
							"host": [
								"localhost"
							],
							"port": "5000",
							"path": [
								"restaurants",
								"66af7f40e70a3ed181fc70a1"
							]
						}
					},
					"response": []
				}
			]
		},
		{
			"name": "Events",
			"item": [
				{
					"name": "AddEvent",
					"request": {
						"method": "POST",
						"header": [],
						"body": {
							"mode": "raw",
							"raw": "{\r\n    \"name\": \"req.body.name\",\r\n    \"location\": \"req.body.location\",\r\n    \"description\": \"req.body.description\",\r\n    \"eventDate\": \"2024-05-23\",\r\n    \"eventEndDate\": \"2024-05-23\"\r\n}",
							"options": {
								"raw": {
									"language": "json"
								}
							}
						},
						"url": {
							"raw": "http://localhost:5000/events",
							"protocol": "http",
							"host": [
								"localhost"
							],
							"port": "5000",
							"path": [
								"events"
							]
						}
					},
					"response": []
				},
				{
					"name": "GetEvents",
					"request": {
						"method": "GET",
						"header": [],
						"url": {
							"raw": "http://localhost:5000/events",
							"protocol": "http",
							"host": [
								"localhost"
							],
							"port": "5000",
							"path": [
								"events"
							]
						}
					},
					"response": []
				},
				{
					"name": "DeleteEvent",
					"request": {
						"method": "DELETE",
						"header": [],
						"url": {
							"raw": "http://localhost:5000/events/66b0044ff84a04f50fe62842",
							"protocol": "http",
							"host": [
								"localhost"
							],
							"port": "5000",
							"path": [
								"events",
								"66b0044ff84a04f50fe62842"
							]
						}
					},
					"response": []
				},
				{
					"name": "UpdateEvent",
					"request": {
						"method": "PUT",
						"header": [],
						"body": {
							"mode": "raw",
							"raw": "{\r\n    \"name\": \"yeojfg\",\r\n    \"location\": \"req.bfdsfsdgren\",\r\n    \"description\": \"req.body.gregredescription\",\r\n    \"eventDate\": \"2024-05-23\",\r\n    \"eventEndDate\": \"2024-05-23\"\r\n}",
							"options": {
								"raw": {
									"language": "json"
								}
							}
						},
						"url": {
							"raw": "http://localhost:5000/events/66b0044ff84a04f50fe62842",
							"protocol": "http",
							"host": [
								"localhost"
							],
							"port": "5000",
							"path": [
								"events",
								"66b0044ff84a04f50fe62842"
							]
						}
					},
					"response": []
				}
			]
		}
	]
}